mutalyzer/__init__.py
mutalyzer/algebra.py
mutalyzer/back_translator.py
mutalyzer/checker.py
mutalyzer/cli.py
mutalyzer/description.py
mutalyzer/description_alt.py
mutalyzer/description_extractor.py
mutalyzer/description_model.py
mutalyzer/errors.py
mutalyzer/gtoc.py
mutalyzer/infos.py
mutalyzer/mapper.py
mutalyzer/mutator.py
mutalyzer/normalizer.py
mutalyzer/position_converter.py
mutalyzer/protein.py
mutalyzer/reference.py
mutalyzer/spdi_converter.py
mutalyzer/util.py
mutalyzer/validation.py
mutalyzer/viewer.py
mutalyzer/converter/__init__.py
mutalyzer/converter/extras.py
mutalyzer/converter/to_delins.py
mutalyzer/converter/to_hgvs_coordinates.py
mutalyzer/converter/to_hgvs_indexing.py
mutalyzer/converter/to_internal_coordinates.py
mutalyzer/converter/to_internal_indexing.py
mutalyzer/converter/to_rna.py
mutalyzer/converter/variants_de_to_hgvs.py
mutalyzer-3.1.1.dist-info/licenses/LICENSE
mutalyzer-3.1.1.dist-info/METADATA
mutalyzer-3.1.1.dist-info/WHEEL
mutalyzer-3.1.1.dist-info/entry_points.txt
mutalyzer-3.1.1.dist-info/top_level.txt
mutalyzer-3.1.1.dist-info/RECORD
