Metadata-Version: 2.4
Name: mutalyzer
Version: 3.1.1
Summary: Mutalyzer HGVS variant description tools.
Home-page: https://github.com/mutalyzer/mutalyzer
Author: Mihai Lefter
Author-email: M.Lefter@lumc.nl
License: MIT
Keywords: Mutalyzer,HGVS
Classifier: Intended Audience :: Science/Research
Classifier: Intended Audience :: Developers
Classifier: Operating System :: OS Independent
Classifier: Programming Language :: Python :: 3
Classifier: Topic :: Scientific/Engineering :: Bio-Informatics
License-File: LICENSE
Requires-Dist: mutalyzer-hgvs-parser>=0.3.4
Requires-Dist: mutalyzer-spdi-parser>=0.3.1
Requires-Dist: mutalyzer-retriever>=0.3.3
Requires-Dist: mutalyzer-mutator>=0.2.0
Requires-Dist: mutalyzer_crossmapper>=2.0.1
Requires-Dist: mutalyzer-backtranslate>=1.0.0
Requires-Dist: description-extractor>=3.0.0
Requires-Dist: mutalyzer-algebra>=1.5.0
Provides-Extra: dev
Requires-Dist: coverage; extra == "dev"
Requires-Dist: flake8; extra == "dev"
Requires-Dist: pytest; extra == "dev"
Requires-Dist: setuptools; extra == "dev"
Requires-Dist: twine; extra == "dev"
Dynamic: license-file
